umongo/__init__.py
umongo/abstract.py
umongo/builder.py
umongo/data_objects.py
umongo/data_proxy.py
umongo/document.py
umongo/embedded_document.py
umongo/exceptions.py
umongo/expose_missing.py
umongo/fields.py
umongo/i18n.py
umongo/indexes.py
umongo/instance.py
umongo/marshmallow_bonus.py
umongo/mixin.py
umongo/query_mapper.py
umongo/template.py
umongo/validate.py
umongo/frameworks/__init__.py
umongo/frameworks/mongomock.py
umongo/frameworks/motor_asyncio.py
umongo/frameworks/pymongo.py
umongo/frameworks/tools.py
umongo/frameworks/txmongo.py
umongo-3.0.1.dist-info/AUTHORS.rst
umongo-3.0.1.dist-info/LICENSE
umongo-3.0.1.dist-info/METADATA
umongo-3.0.1.dist-info/WHEEL
umongo-3.0.1.dist-info/top_level.txt
umongo-3.0.1.dist-info/RECORD
