Metadata-Version: 2.1
Name: umongo
Version: 3.0.1
Summary: sync/async MongoDB ODM, yes.
Home-page: https://github.com/touilleMan/umongo
Author: Emmanuel Leblond, Jérôme Lafréchoux
Author-email: jerome@jolimont.fr
License: MIT
Keywords: umongo mongodb pymongo txmongo motor mongomock asyncio twisted
Platform: UNKNOWN
Classifier: Development Status :: 5 - Production/Stable
Classifier: Intended Audience :: Developers
Classifier: License :: OSI Approved :: MIT License
Classifier: Natural Language :: English
Classifier: Programming Language :: Python :: 3
Classifier: Programming Language :: Python :: 3.7
Classifier: Programming Language :: Python :: 3.8
Classifier: Programming Language :: Python :: 3.9
Classifier: Programming Language :: Python :: 3 :: Only
Requires-Python: >=3.7
Provides-Extra: motor
Provides-Extra: txmongo
Provides-Extra: mongomock
License-File: LICENSE
License-File: AUTHORS.rst
